command_runner/__init__.py
command_runner/elevate.py
command_runner-1.7.5.dist-info/LICENSE
command_runner-1.7.5.dist-info/METADATA
command_runner-1.7.5.dist-info/WHEEL
command_runner-1.7.5.dist-info/top_level.txt
command_runner-1.7.5.dist-info/RECORD
