Metadata-Version: 2.1
Name: command_runner
Version: 1.7.5
Summary: Platform agnostic command and shell execution tool, also allows UAC/sudo privilege elevation
Home-page: https://github.com/netinvent/command_runner
Author: NetInvent - Orsiris de Jong
Author-email: contact@netinvent.fr
License: BSD
Keywords: shell,execution,subprocess,check_output,wrapper,uac,sudo,elevate,privilege
Classifier: Development Status :: 5 - Production/Stable
Classifier: Intended Audience :: Developers
Classifier: Topic :: Software Development
Classifier: Topic :: System
Classifier: Topic :: System :: Operating System
Classifier: Topic :: System :: Shells
Classifier: Programming Language :: Python
Classifier: Programming Language :: Python :: 3
Classifier: Programming Language :: Python :: Implementation :: CPython
Classifier: Programming Language :: Python :: Implementation :: PyPy
Classifier: Operating System :: POSIX :: Linux
Classifier: Operating System :: POSIX :: BSD :: FreeBSD
Classifier: Operating System :: POSIX :: BSD :: NetBSD
Classifier: Operating System :: POSIX :: BSD :: OpenBSD
Classifier: Operating System :: Microsoft
Classifier: Operating System :: Microsoft :: Windows
Classifier: License :: OSI Approved :: BSD License
Requires-Python: >=2.7
License-File: LICENSE
Requires-Dist: psutil >=5.6.0
